setup.cfg
setup.py
bin/lillebror
lillebror/__init__.py
lillebror/cli.py
lillebror/monitor.py
lillebror/outputs.py
lillebror/samplers.py
lillebror/version.py
lillebror.egg-info/PKG-INFO
lillebror.egg-info/SOURCES.txt
lillebror.egg-info/dependency_links.txt
lillebror.egg-info/requires.txt
lillebror.egg-info/top_level.txt