Metadata-Version: 1.0
Name: lillebror
Version: 0.2.2
Summary: Library for process monitoring and logging
Home-page: https://github.com/looplab/lillebror
Author: Max Persson
Author-email: max@looplab.se
License: Apache License 2.0
Platform: UNKNOWN
Classifier: Development Status :: 3 - Alpha
Classifier: Environment :: Console
Classifier: Intended Audience :: Developers
Classifier: License :: OSI Approved :: Apache Software License
Classifier: Programming Language :: Python
Classifier: Programming Language :: Python :: 2
Classifier: Programming Language :: Python :: 2.6
Classifier: Topic :: Software Development :: Libraries :: Python Modules
Classifier: Topic :: System :: Networking
